{
    "technical_requirements": {
        "type": "object",
        "properties": {
            "metadata_file_name": {
                "type": "string"
            },
            "metadata_index": {
                "type": "string"
            }
        }
    },
	"technical_requirements_atax": {
        "type": "object",
        "properties": {
            "specimen_file_name": {
                "type": "string"
            },
            "specimen_index": {
                "type": "string"
            },
			"files_file_name": {
                "type": "string"
            },
            "files_index": {
                "type": "string"
            }
        }
    }
}
